zombiecipheer-1.0.0.dist-info/licenses/LICENSE
zombiecipher/__init__.py
zombiecipheer-1.0.0.dist-info/METADATA
zombiecipheer-1.0.0.dist-info/WHEEL
zombiecipheer-1.0.0.dist-info/top_level.txt
zombiecipheer-1.0.0.dist-info/RECORD
