Metadata-Version: 2.4
Name: zombiecipheer
Version: 1.0.0
Summary: Simple XOR-based encryption library called ZombieCipher
Author: adam
Classifier: Programming Language :: Python :: 3
Classifier: License :: OSI Approved :: MIT License
Classifier: Operating System :: OS Independent
Requires-Python: >=3.6
License-File: LICENSE
Dynamic: author
Dynamic: classifier
Dynamic: license-file
Dynamic: requires-python
Dynamic: summary
